LICENSE
README.md
setup.py
polymedia/__init__.py
polymedia/hal.py
polymedia/poly.py
polymedia/restclient.py
polymedia/wstl.py
polymedia.egg-info/PKG-INFO
polymedia.egg-info/SOURCES.txt
polymedia.egg-info/dependency_links.txt
polymedia.egg-info/requires.txt
polymedia.egg-info/top_level.txt