Metadata-Version: 2.1
Name: polymedia
Version: 0.2.1
Summary: A polyglot hypermedia library for python ReSTful services
Home-page: https://github.com/michalporeba/polymedia
Author: Michal Poreba
License: MIT
Platform: UNKNOWN
Classifier: Development Status :: 3 - Alpha
Classifier: License :: OSI Approved :: MIT License
Classifier: Programming Language :: Python :: 3
Classifier: Intended Audience :: Developers
Classifier: Topic :: Software Development
License-File: LICENSE
